pybess_grpc/__init__.py
pybess_grpc/bess.py
pybess_grpc/module.py
pybess_grpc/pm_import.py
pybess_grpc/port.py
pybess_grpc/protobuf_to_dict.py
pybess_grpc/test_bess.py
pybess_grpc/test_protobuf_to_dict.py
pybess_grpc/builtin_pb/__init__.py
pybess_grpc/builtin_pb/bess_msg_pb2.py
pybess_grpc/builtin_pb/bess_msg_pb2_grpc.py
pybess_grpc/builtin_pb/error_pb2.py
pybess_grpc/builtin_pb/error_pb2_grpc.py
pybess_grpc/builtin_pb/module_msg_pb2.py
pybess_grpc/builtin_pb/module_msg_pb2_grpc.py
pybess_grpc/builtin_pb/service_pb2.py
pybess_grpc/builtin_pb/service_pb2_grpc.py
pybess_grpc/builtin_pb/util_msg_pb2.py
pybess_grpc/builtin_pb/util_msg_pb2_grpc.py
pybess_grpc/builtin_pb/ports/__init__.py
pybess_grpc/builtin_pb/ports/port_msg_pb2.py
pybess_grpc/builtin_pb/ports/port_msg_pb2_grpc.py
pybess_grpc/plugin_pb/__init__.py
pybess_grpc/plugin_pb/ports/__init__.py
pybess_grpc-0.0.4.post5.dist-info/LICENSE.txt
pybess_grpc-0.0.4.post5.dist-info/METADATA
pybess_grpc-0.0.4.post5.dist-info/WHEEL
pybess_grpc-0.0.4.post5.dist-info/top_level.txt
pybess_grpc-0.0.4.post5.dist-info/RECORD
