Metadata-Version: 2.1
Name: pybess-grpc
Version: 0.0.4.post5
Summary: Python Bindings to Interact with BESS GRPC Daemon
Home-page: UNKNOWN
Author: Remi Vichery
Author-email: remi.vichery@gmail.com
License: UNKNOWN
Platform: UNKNOWN
Requires-Dist: grpcio (==1.27.2)
Requires-Dist: protobuf (==3.11.3)
